dictionnary_objectify/__init__.py
dictionnary_objectify/example.py
dictionnary_objectify-1.0.1.dist-info/LICENSE
dictionnary_objectify-1.0.1.dist-info/METADATA
dictionnary_objectify-1.0.1.dist-info/WHEEL
dictionnary_objectify-1.0.1.dist-info/top_level.txt
dictionnary_objectify-1.0.1.dist-info/RECORD
