Metadata-Version: 2.1
Name: dictionnary-objectify
Version: 1.0.1
Summary: A small packages who allows you to create object from dictionnarys
Author-email: moyonenzo <moyon_e@etna-alternance.net>
Project-URL: Homepage, https://github.com/moyonenzo/py-dictionnary-object
Project-URL: Issues, https://github.com/moyonenzo/py-dictionnary-object/issues
Classifier: Programming Language :: Python :: 3
Classifier: License :: OSI Approved :: MIT License
Classifier: Operating System :: OS Independent
Requires-Python: >=3.8
License-File: LICENSE
Requires-Dist: forbiddenfruit
